pyiso4/LTWA_20210702.csv
pyiso4/__init__.py
pyiso4/lexer.py
pyiso4/ltwa.py
pyiso4/normalize_string.py
pyiso4/prefix_tree.py
pyiso4/script.py
pyiso4/stopwords.txt
pyiso4-0.1.6.dist-info/LICENSE
pyiso4-0.1.6.dist-info/METADATA
pyiso4-0.1.6.dist-info/WHEEL
pyiso4-0.1.6.dist-info/entry_points.txt
pyiso4-0.1.6.dist-info/top_level.txt
pyiso4-0.1.6.dist-info/RECORD
