Metadata-Version: 2.1
Name: pyiso4
Version: 0.1.6
Summary: Abbreviate a scientific journal title following the ISO-4 rules
Author-email: Pierre Beaujean <pierre.beaujean@unamur.be>
License: MIT License
Classifier: Development Status :: 4 - Beta
Classifier: License :: OSI Approved :: MIT License
Classifier: Natural Language :: English
Classifier: Operating System :: OS Independent
Classifier: Programming Language :: Python
Classifier: Programming Language :: Python :: 3.8
Classifier: Programming Language :: Python :: 3.9
Classifier: Programming Language :: Python :: 3.10
Classifier: Programming Language :: Python :: 3.11
Classifier: Programming Language :: Python :: 3.12
Requires-Python: >=3.8
License-File: LICENSE
Requires-Dist: unidecode
Provides-Extra: dev
Requires-Dist: flake8 ; extra == 'dev'
Requires-Dist: flake8-quotes ; extra == 'dev'
Requires-Dist: autopep8 ; extra == 'dev'
Requires-Dist: bump2version ; extra == 'dev'
